LICENSE
README.md
setup.cfg
setup.py
bones/ipykernel/bones_kernel.py
bones/libs/on_demand/range.py
coppertop_bones_demo.egg-info/PKG-INFO
coppertop_bones_demo.egg-info/SOURCES.txt
coppertop_bones_demo.egg-info/dependency_links.txt
coppertop_bones_demo.egg-info/not-zip-safe
coppertop_bones_demo.egg-info/top_level.txt
dm/canvas.py
dm/orient_eigens.py
dm/pmf.py
dm/utils.py
dm/_structs/_tvarray.py
dm/_structs/_tvlist.py
dm/_structs/_tvmap.py
dm/_structs/_tvstruct.py
dm/core/__init__.py
dm/core/accessing.py
dm/core/combining.py
dm/core/complex.py
dm/core/converting.py
dm/core/datetime.py
dm/core/dividing.py
dm/core/files.py
dm/core/generating.py
dm/core/linalg.py
dm/core/maths.py
dm/core/misc.py
dm/core/range.py
dm/core/reordering.py
dm/core/searching.py
dm/core/stats.py
dm/core/stdio.py
dm/core/structs.py
dm/core/testing.py
dm/core/text.py
dm/core/transforming.py
dm/core/types.py
dm/core/unicode.py
dm/core/vec.py
dm/core/_linalg/core.py
dm/core/_linalg/decomp.py
dm/core/_stats/core.py
dm/examples/ex_all.py
dm/examples/ex_count_lines_jsp.py
dm/examples/ex_deferred.py
dm/examples/ex_format.py
dm/examples/ex_format_calendar.py
dm/examples/ex_fx.py
dm/examples/ex_lazy_vs_eager.py
dm/examples/ex_linalg.py
dm/examples/ex_linked_list.py
dm/examples/ex_misc.py
dm/examples/ex_raiseLessPipe.py
dm/examples/ex_spaceships.py
dm/examples/ex_ytm_cov.py
dm/examples/cluedo/algos.py
dm/examples/cluedo/cards.py
dm/examples/cluedo/core.py
dm/examples/cluedo/games.py
dm/examples/cluedo/numpy_pmf.py
dm/examples/cluedo/partitions_bruteforce.py
dm/examples/cluedo/partitions_cptb_style.py
dm/examples/cluedo/partitions_ml_style.py
dm/examples/cluedo/reports.py
dm/examples/cluedo/utils.py