Metadata-Version: 2.1
Name: coppertop-bones-demo
Version: 2022.7.30
Summary: Some batteries Python didn't come with
Home-page: https://github.com/DangerMouseB/coppertop-bones-demo
Download-URL: 
Author: David Briant
Author-email: dangermouseb@forwarding.cc
License: BSD
Keywords: piping,pipeline,pipe,functional
Classifier: Development Status :: 4 - Beta
Classifier: Intended Audience :: Developers
Classifier: Intended Audience :: End Users/Desktop
Classifier: Intended Audience :: Science/Research
Classifier: Topic :: Utilities
Classifier: License :: OSI Approved :: BSD License
Classifier: Programming Language :: Python :: 3.8
Classifier: Programming Language :: Python :: 3.9
Classifier: Programming Language :: Python :: 3.10
Requires-Python: >=3.8
License-File: LICENSE
